<?xml version="1.0" encoding="UTF-8"?><?xml-stylesheet type='text/xsl' href='_UpgradeReport_Files/UpgradeReport.xslt'?><UpgradeLog>
<Properties><Property Name="Solution" Value="TableHockey1">
</Property><Property Name="Solution File" Value="C:\Users\jgafvels\Documents\Visual Studio 2008\Projects\TableHockey1\TableHockey1.sln">
</Property><Property Name="User Options File" Value="C:\Users\jgafvels\Documents\Visual Studio 2008\Projects\TableHockey1\TableHockey1.suo">
</Property><Property Name="Date" Value="den 1 februari 2012">
</Property><Property Name="Time" Value="11:55">
</Property></Properties><Event ErrorLevel="0" Project="" Source="TableHockey1.sln" Description="File successfully backed up as C:\Users\jgafvels\Documents\Visual Studio 2008\Projects\TableHockey1\Backup\TableHockey1.sln">
</Event><Event ErrorLevel="0" Project="" Source="TableHockey1.suo" Description="File successfully backed up as C:\Users\jgafvels\Documents\Visual Studio 2008\Projects\TableHockey1\Backup\TableHockey1.suo">
</Event><Event ErrorLevel="0" Project="TableHockey1" Source="TableHockey1\TableHockey1.csproj" Description="Project file successfully backed up as C:\Users\jgafvels\Documents\Visual Studio 2008\Projects\TableHockey1\Backup\TableHockey1\TableHockey1.csproj">
</Event><Event ErrorLevel="0" Project="TableHockey1" Source="TableHockey1\TableHockey1.csproj.user" Description="Project user file successfully backed up as C:\Users\jgafvels\Documents\Visual Studio 2008\Projects\TableHockey1\Backup\TableHockey1\TableHockey1.csproj.user">
</Event><Event ErrorLevel="0" Project="TableHockey1" Source="TableHockey1\pgMain.aspx.cs" Description="File successfully backed up as C:\Users\jgafvels\Documents\Visual Studio 2008\Projects\TableHockey1\Backup\TableHockey1\pgMain.aspx.cs">
</Event><Event ErrorLevel="0" Project="TableHockey1" Source="TableHockey1\pgMain.aspx.designer.cs" Description="File successfully backed up as C:\Users\jgafvels\Documents\Visual Studio 2008\Projects\TableHockey1\Backup\TableHockey1\pgMain.aspx.designer.cs">
</Event><Event ErrorLevel="0" Project="TableHockey1" Source="TableHockey1\pgTournamentTool.aspx.cs" Description="File successfully backed up as C:\Users\jgafvels\Documents\Visual Studio 2008\Projects\TableHockey1\Backup\TableHockey1\pgTournamentTool.aspx.cs">
</Event><Event ErrorLevel="0" Project="TableHockey1" Source="TableHockey1\pgTournamentTool.aspx.designer.cs" Description="File successfully backed up as C:\Users\jgafvels\Documents\Visual Studio 2008\Projects\TableHockey1\Backup\TableHockey1\pgTournamentTool.aspx.designer.cs">
</Event><Event ErrorLevel="0" Project="TableHockey1" Source="TableHockey1\Properties\AssemblyInfo.cs" Description="File successfully backed up as C:\Users\jgafvels\Documents\Visual Studio 2008\Projects\TableHockey1\Backup\TableHockey1\Properties\AssemblyInfo.cs">
</Event><Event ErrorLevel="0" Project="TableHockey1" Source="TableHockey1\pgMain.aspx" Description="File successfully backed up as C:\Users\jgafvels\Documents\Visual Studio 2008\Projects\TableHockey1\Backup\TableHockey1\pgMain.aspx">
</Event><Event ErrorLevel="0" Project="TableHockey1" Source="TableHockey1\Web.config" Description="File successfully backed up as C:\Users\jgafvels\Documents\Visual Studio 2008\Projects\TableHockey1\Backup\TableHockey1\Web.config">
</Event><Event ErrorLevel="0" Project="TableHockey1" Source="TableHockey1\images\img01.jpg" Description="File successfully backed up as C:\Users\jgafvels\Documents\Visual Studio 2008\Projects\TableHockey1\Backup\TableHockey1\images\img01.jpg">
</Event><Event ErrorLevel="0" Project="TableHockey1" Source="TableHockey1\images\uhss.gif" Description="File successfully backed up as C:\Users\jgafvels\Documents\Visual Studio 2008\Projects\TableHockey1\Backup\TableHockey1\images\uhss.gif">
</Event><Event ErrorLevel="0" Project="TableHockey1" Source="TableHockey1\MasterPage.master" Description="File successfully backed up as C:\Users\jgafvels\Documents\Visual Studio 2008\Projects\TableHockey1\Backup\TableHockey1\MasterPage.master">
</Event><Event ErrorLevel="0" Project="TableHockey1" Source="TableHockey1\pgTournamentTool.aspx" Description="File successfully backed up as C:\Users\jgafvels\Documents\Visual Studio 2008\Projects\TableHockey1\Backup\TableHockey1\pgTournamentTool.aspx">
</Event><Event ErrorLevel="0" Project="TableHockey1" Source="TableHockey1\styles\Styles.css" Description="File successfully backed up as C:\Users\jgafvels\Documents\Visual Studio 2008\Projects\TableHockey1\Backup\TableHockey1\styles\Styles.css">
</Event><Event ErrorLevel="0" Project="TableHockey1" Source="TableHockey1\TableHockey1.csproj" Description="Project converted successfully">
</Event><Event ErrorLevel="3" Project="TableHockey1" Source="TableHockey1\TableHockey1.csproj" Description="Converted">
</Event><Event ErrorLevel="0" Project="" Source="TableHockey1.sln" Description="Solution converted successfully">
</Event><Event ErrorLevel="3" Project="" Source="TableHockey1.sln" Description="Converted">
</Event><Event ErrorLevel="0" Project="TableHockey1" Source="TableHockey1\TableHockey1.csproj" Description="Scan complete: Upgrade not required for project files.">
</Event></UpgradeLog>